theanets/__init__.py
theanets/activations.py
theanets/feedforward.py
theanets/graph.py
theanets/losses.py
theanets/main.py
theanets/recurrent.py
theanets/regularizers.py
theanets/trainer.py
theanets/util.py
theanets/layers/__init__.py
theanets/layers/base.py
theanets/layers/convolution.py
theanets/layers/feedforward.py
theanets/layers/recurrent.py
theanets/layers/tree.py
theanets-0.7.3.dist-info/DESCRIPTION.rst
theanets-0.7.3.dist-info/METADATA
theanets-0.7.3.dist-info/RECORD
theanets-0.7.3.dist-info/WHEEL
theanets-0.7.3.dist-info/metadata.json
theanets-0.7.3.dist-info/top_level.txt
