Metadata-Version: 2.0
Name: theanets
Version: 0.7.3
Summary: Feedforward and recurrent neural nets using Theano
Home-page: http://github.com/lmjohns3/theanets
Author: Leif Johnson
Author-email: leif@lmjohns3.com
License: MIT
Keywords: machine-learning neural-network deep-neural-network recurrent-neural-network autoencoder sparse-autoencoder classifier theano
Platform: UNKNOWN
Classifier: Development Status :: 3 - Alpha
Classifier: Intended Audience :: Science/Research
Classifier: License :: OSI Approved :: MIT License
Classifier: Operating System :: OS Independent
Classifier: Topic :: Scientific/Engineering
Classifier: Topic :: Scientific/Engineering :: Artificial Intelligence
Requires-Dist: climate
Requires-Dist: downhill
Requires-Dist: theano
